{
  "totalWords": 68760,
  "processedWords": 1720,
  "definitionsUpdated": 1684,
  "owadPhrasesUpdated": 1719,
  "distractorsUpdated": 1720,
  "errors": 80,
  "errorWords": [
    "piping",
    "mechanization",
    "mechanisation",
    "launching",
    "launch",
    "impulse",
    "leaning",
    "impulsion",
    "impetus",
    "firewall",
    "roll",
    "smear",
    "hurl",
    "toss",
    "fumble",
    "fling",
    "heaving",
    "fastball",
    "heater",
    "jog",
    "massage",
    "therapy",
    "nourishment",
    "bungle",
    "balk",
    "bender",
    "bullet",
    "screwball",
    "pulling",
    "jumper",
    "shape",
    "pushing",
    "nudge",
    "pressing",
    "bundling",
    "shove",
    "jostle",
    "elbowing",
    "haulage",
    "form",
    "groundball",
    "prognosis",
    "hematemesis",
    "leaping",
    "headshot",
    "hyperemesis",
    "sending",
    "transmittal",
    "transmitting",
    "remitment",
    "wheeling",
    "countershot",
    "skeet",
    "shellfire",
    "gunfight",
    "gunplay",
    "shootout",
    "fielding",
    "tko",
    "scorcher",
    "plunker",
    "bingle",
    "roundhouse",
    "strikeout",
    "backhander",
    "smacking",
    "smacker",
    "spank",
    "counterpunch",
    "tickling",
    "converging",
    "adjunction",
    "smooch",
    "autopsy",
    "reexamination",
    "necropsy",
    "checkup",
    "ophthalmoscopy",
    "palpation",
    "titillation"
  ],
  "startTime": 1742095471399,
  "batches": [
    {
      "batchNumber": 1,
      "wordCount": 40,
      "definitionsUpdated": 36,
      "owadPhrasesUpdated": 40,
      "distractorsUpdated": 40,
      "errors": 0,
      "startTime": 1742095474043,
      "endTime": 1742095512533,
      "elapsedTimeMs": 38490,
      "elapsedTimeMin": 0.6
    },
    {
      "batchNumber": 2,
      "wordCount": 40,
      "definitionsUpdated": 34,
      "owadPhrasesUpdated": 40,
      "distractorsUpdated": 40,
      "errors": 0,
      "startTime": 1742095512780,
      "endTime": 1742095551029,
      "elapsedTimeMs": 38249,
      "elapsedTimeMin": 0.6
    },
    {
      "batchNumber": 3,
      "wordCount": 40,
      "definitionsUpdated": 36,
      "owadPhrasesUpdated": 40,
      "distractorsUpdated": 40,
      "errors": 0,
      "startTime": 1742095551280,
      "endTime": 1742095590077,
      "elapsedTimeMs": 38797,
      "elapsedTimeMin": 0.6
    },
    {
      "batchNumber": 4,
      "wordCount": 40,
      "definitionsUpdated": 40,
      "owadPhrasesUpdated": 40,
      "distractorsUpdated": 40,
      "errors": 0,
      "startTime": 1742095590317,
      "endTime": 1742095628809,
      "elapsedTimeMs": 38492,
      "elapsedTimeMin": 0.6
    },
    {
      "batchNumber": 5,
      "wordCount": 40,
      "definitionsUpdated": 39,
      "owadPhrasesUpdated": 40,
      "distractorsUpdated": 40,
      "errors": 0,
      "startTime": 1742095629126,
      "endTime": 1742095668480,
      "elapsedTimeMs": 39354,
      "elapsedTimeMin": 0.7
    },
    {
      "batchNumber": 6,
      "wordCount": 40,
      "definitionsUpdated": 40,
      "owadPhrasesUpdated": 40,
      "distractorsUpdated": 40,
      "errors": 0,
      "startTime": 1742095668719,
      "endTime": 1742095709084,
      "elapsedTimeMs": 40365,
      "elapsedTimeMin": 0.7
    },
    {
      "batchNumber": 7,
      "wordCount": 40,
      "definitionsUpdated": 39,
      "owadPhrasesUpdated": 40,
      "distractorsUpdated": 40,
      "errors": 0,
      "startTime": 1742095709376,
      "endTime": 1742095750944,
      "elapsedTimeMs": 41568,
      "elapsedTimeMin": 0.7
    },
    {
      "batchNumber": 8,
      "wordCount": 40,
      "definitionsUpdated": 39,
      "owadPhrasesUpdated": 40,
      "distractorsUpdated": 40,
      "errors": 0,
      "startTime": 1742095751186,
      "endTime": 1742095789686,
      "elapsedTimeMs": 38500,
      "elapsedTimeMin": 0.6
    },
    {
      "batchNumber": 9,
      "wordCount": 40,
      "definitionsUpdated": 40,
      "owadPhrasesUpdated": 40,
      "distractorsUpdated": 40,
      "errors": 0,
      "startTime": 1742095789988,
      "endTime": 1742095830791,
      "elapsedTimeMs": 40803,
      "elapsedTimeMin": 0.7
    },
    {
      "batchNumber": 10,
      "wordCount": 40,
      "definitionsUpdated": 40,
      "owadPhrasesUpdated": 40,
      "distractorsUpdated": 40,
      "errors": 0,
      "startTime": 1742095831043,
      "endTime": 1742095870795,
      "elapsedTimeMs": 39752,
      "elapsedTimeMin": 0.7
    },
    {
      "batchNumber": 11,
      "wordCount": 40,
      "definitionsUpdated": 40,
      "owadPhrasesUpdated": 40,
      "distractorsUpdated": 40,
      "errors": 0,
      "startTime": 1742095871095,
      "endTime": 1742095915944,
      "elapsedTimeMs": 44849,
      "elapsedTimeMin": 0.7
    },
    {
      "batchNumber": 12,
      "wordCount": 40,
      "definitionsUpdated": 40,
      "owadPhrasesUpdated": 40,
      "distractorsUpdated": 40,
      "errors": 0,
      "startTime": 1742095916194,
      "endTime": 1742095956377,
      "elapsedTimeMs": 40183,
      "elapsedTimeMin": 0.7
    },
    {
      "batchNumber": 13,
      "wordCount": 40,
      "definitionsUpdated": 0,
      "owadPhrasesUpdated": 0,
      "distractorsUpdated": 0,
      "errors": 40,
      "startTime": 1742095956627,
      "endTime": 1742095974598,
      "elapsedTimeMs": 17971,
      "elapsedTimeMin": 0.3
    },
    {
      "batchNumber": 14,
      "wordCount": 40,
      "definitionsUpdated": 38,
      "owadPhrasesUpdated": 40,
      "distractorsUpdated": 40,
      "errors": 0,
      "startTime": 1742095974856,
      "endTime": 1742096012832,
      "elapsedTimeMs": 37976,
      "elapsedTimeMin": 0.6
    },
    {
      "batchNumber": 15,
      "wordCount": 40,
      "definitionsUpdated": 40,
      "owadPhrasesUpdated": 40,
      "distractorsUpdated": 40,
      "errors": 0,
      "startTime": 1742096013082,
      "endTime": 1742096053243,
      "elapsedTimeMs": 40161,
      "elapsedTimeMin": 0.7
    },
    {
      "batchNumber": 16,
      "wordCount": 40,
      "definitionsUpdated": 37,
      "owadPhrasesUpdated": 40,
      "distractorsUpdated": 40,
      "errors": 0,
      "startTime": 1742096053497,
      "endTime": 1742096102128,
      "elapsedTimeMs": 48631,
      "elapsedTimeMin": 0.8
    },
    {
      "batchNumber": 17,
      "wordCount": 40,
      "definitionsUpdated": 40,
      "owadPhrasesUpdated": 39,
      "distractorsUpdated": 40,
      "errors": 0,
      "startTime": 1742096102377,
      "endTime": 1742096144464,
      "elapsedTimeMs": 42087,
      "elapsedTimeMin": 0.7
    },
    {
      "batchNumber": 18,
      "wordCount": 40,
      "definitionsUpdated": 37,
      "owadPhrasesUpdated": 40,
      "distractorsUpdated": 40,
      "errors": 0,
      "startTime": 1742096144712,
      "endTime": 1742096184441,
      "elapsedTimeMs": 39729,
      "elapsedTimeMin": 0.7
    },
    {
      "batchNumber": 19,
      "wordCount": 40,
      "definitionsUpdated": 40,
      "owadPhrasesUpdated": 40,
      "distractorsUpdated": 40,
      "errors": 0,
      "startTime": 1742096184747,
      "endTime": 1742096227052,
      "elapsedTimeMs": 42305,
      "elapsedTimeMin": 0.7
    },
    {
      "batchNumber": 20,
      "wordCount": 40,
      "definitionsUpdated": 40,
      "owadPhrasesUpdated": 40,
      "distractorsUpdated": 40,
      "errors": 0,
      "startTime": 1742096227295,
      "endTime": 1742096276217,
      "elapsedTimeMs": 48922,
      "elapsedTimeMin": 0.8
    },
    {
      "batchNumber": 21,
      "wordCount": 40,
      "definitionsUpdated": 40,
      "owadPhrasesUpdated": 40,
      "distractorsUpdated": 40,
      "errors": 0,
      "startTime": 1742096276599,
      "endTime": 1742096317973,
      "elapsedTimeMs": 41374,
      "elapsedTimeMin": 0.7
    },
    {
      "batchNumber": 22,
      "wordCount": 40,
      "definitionsUpdated": 38,
      "owadPhrasesUpdated": 40,
      "distractorsUpdated": 40,
      "errors": 0,
      "startTime": 1742096318280,
      "endTime": 1742096360356,
      "elapsedTimeMs": 42076,
      "elapsedTimeMin": 0.7
    },
    {
      "batchNumber": 23,
      "wordCount": 40,
      "definitionsUpdated": 39,
      "owadPhrasesUpdated": 40,
      "distractorsUpdated": 40,
      "errors": 0,
      "startTime": 1742096360607,
      "endTime": 1742096401119,
      "elapsedTimeMs": 40512,
      "elapsedTimeMin": 0.7
    },
    {
      "batchNumber": 24,
      "wordCount": 40,
      "definitionsUpdated": 40,
      "owadPhrasesUpdated": 40,
      "distractorsUpdated": 40,
      "errors": 0,
      "startTime": 1742096401354,
      "endTime": 1742096441882,
      "elapsedTimeMs": 40528,
      "elapsedTimeMin": 0.7
    },
    {
      "batchNumber": 25,
      "wordCount": 40,
      "definitionsUpdated": 40,
      "owadPhrasesUpdated": 40,
      "distractorsUpdated": 40,
      "errors": 0,
      "startTime": 1742096442124,
      "endTime": 1742096481064,
      "elapsedTimeMs": 38940,
      "elapsedTimeMin": 0.6
    },
    {
      "batchNumber": 26,
      "wordCount": 40,
      "definitionsUpdated": 40,
      "owadPhrasesUpdated": 40,
      "distractorsUpdated": 40,
      "errors": 0,
      "startTime": 1742096481310,
      "endTime": 1742096520967,
      "elapsedTimeMs": 39657,
      "elapsedTimeMin": 0.7
    },
    {
      "batchNumber": 27,
      "wordCount": 40,
      "definitionsUpdated": 40,
      "owadPhrasesUpdated": 40,
      "distractorsUpdated": 40,
      "errors": 0,
      "startTime": 1742096521223,
      "endTime": 1742096559563,
      "elapsedTimeMs": 38340,
      "elapsedTimeMin": 0.6
    },
    {
      "batchNumber": 28,
      "wordCount": 40,
      "definitionsUpdated": 39,
      "owadPhrasesUpdated": 40,
      "distractorsUpdated": 40,
      "errors": 0,
      "startTime": 1742096559807,
      "endTime": 1742096600665,
      "elapsedTimeMs": 40858,
      "elapsedTimeMin": 0.7
    },
    {
      "batchNumber": 29,
      "wordCount": 40,
      "definitionsUpdated": 37,
      "owadPhrasesUpdated": 40,
      "distractorsUpdated": 40,
      "errors": 0,
      "startTime": 1742096600924,
      "endTime": 1742096640945,
      "elapsedTimeMs": 40021,
      "elapsedTimeMin": 0.7
    },
    {
      "batchNumber": 30,
      "wordCount": 40,
      "definitionsUpdated": 40,
      "owadPhrasesUpdated": 40,
      "distractorsUpdated": 40,
      "errors": 0,
      "startTime": 1742096641206,
      "endTime": 1742096682833,
      "elapsedTimeMs": 41627,
      "elapsedTimeMin": 0.7
    },
    {
      "batchNumber": 31,
      "wordCount": 40,
      "definitionsUpdated": 40,
      "owadPhrasesUpdated": 40,
      "distractorsUpdated": 40,
      "errors": 0,
      "startTime": 1742096683086,
      "endTime": 1742096725285,
      "elapsedTimeMs": 42199,
      "elapsedTimeMin": 0.7
    },
    {
      "batchNumber": 32,
      "wordCount": 40,
      "definitionsUpdated": 40,
      "owadPhrasesUpdated": 40,
      "distractorsUpdated": 40,
      "errors": 0,
      "startTime": 1742096725527,
      "endTime": 1742096767309,
      "elapsedTimeMs": 41782,
      "elapsedTimeMin": 0.7
    },
    {
      "batchNumber": 33,
      "wordCount": 40,
      "definitionsUpdated": 40,
      "owadPhrasesUpdated": 40,
      "distractorsUpdated": 40,
      "errors": 0,
      "startTime": 1742096767559,
      "endTime": 1742096808779,
      "elapsedTimeMs": 41220,
      "elapsedTimeMin": 0.7
    },
    {
      "batchNumber": 34,
      "wordCount": 40,
      "definitionsUpdated": 0,
      "owadPhrasesUpdated": 0,
      "distractorsUpdated": 0,
      "errors": 40,
      "startTime": 1742096809037,
      "endTime": 1742096817797,
      "elapsedTimeMs": 8760,
      "elapsedTimeMin": 0.1
    },
    {
      "batchNumber": 35,
      "wordCount": 40,
      "definitionsUpdated": 40,
      "owadPhrasesUpdated": 40,
      "distractorsUpdated": 40,
      "errors": 0,
      "startTime": 1742096818372,
      "endTime": 1742096858890,
      "elapsedTimeMs": 40518,
      "elapsedTimeMin": 0.7
    },
    {
      "batchNumber": 36,
      "wordCount": 40,
      "definitionsUpdated": 39,
      "owadPhrasesUpdated": 40,
      "distractorsUpdated": 40,
      "errors": 0,
      "startTime": 1742096859140,
      "endTime": 1742096899486,
      "elapsedTimeMs": 40346,
      "elapsedTimeMin": 0.7
    },
    {
      "batchNumber": 37,
      "wordCount": 40,
      "definitionsUpdated": 40,
      "owadPhrasesUpdated": 40,
      "distractorsUpdated": 40,
      "errors": 0,
      "startTime": 1742096899818,
      "endTime": 1742096941899,
      "elapsedTimeMs": 42081,
      "elapsedTimeMin": 0.7
    },
    {
      "batchNumber": 38,
      "wordCount": 40,
      "definitionsUpdated": 40,
      "owadPhrasesUpdated": 40,
      "distractorsUpdated": 40,
      "errors": 0,
      "startTime": 1742096942160,
      "endTime": 1742096982897,
      "elapsedTimeMs": 40737,
      "elapsedTimeMin": 0.7
    },
    {
      "batchNumber": 39,
      "wordCount": 40,
      "definitionsUpdated": 40,
      "owadPhrasesUpdated": 40,
      "distractorsUpdated": 40,
      "errors": 0,
      "startTime": 1742096983150,
      "endTime": 1742097025437,
      "elapsedTimeMs": 42287,
      "elapsedTimeMin": 0.7
    },
    {
      "batchNumber": 40,
      "wordCount": 40,
      "definitionsUpdated": 37,
      "owadPhrasesUpdated": 40,
      "distractorsUpdated": 40,
      "errors": 0,
      "startTime": 1742097025687,
      "endTime": 1742097066133,
      "elapsedTimeMs": 40446,
      "elapsedTimeMin": 0.7
    },
    {
      "batchNumber": 41,
      "wordCount": 40,
      "definitionsUpdated": 40,
      "owadPhrasesUpdated": 40,
      "distractorsUpdated": 40,
      "errors": 0,
      "startTime": 1742097066389,
      "endTime": 1742097107284,
      "elapsedTimeMs": 40895,
      "elapsedTimeMin": 0.7
    },
    {
      "batchNumber": 42,
      "wordCount": 40,
      "definitionsUpdated": 40,
      "owadPhrasesUpdated": 40,
      "distractorsUpdated": 40,
      "errors": 0,
      "startTime": 1742097107527,
      "endTime": 1742097147906,
      "elapsedTimeMs": 40379,
      "elapsedTimeMin": 0.7
    },
    {
      "batchNumber": 43,
      "wordCount": 40,
      "definitionsUpdated": 40,
      "owadPhrasesUpdated": 40,
      "distractorsUpdated": 40,
      "errors": 0,
      "startTime": 1742097148161,
      "endTime": 1742097193493,
      "elapsedTimeMs": 45332,
      "elapsedTimeMin": 0.8
    },
    {
      "batchNumber": 44,
      "wordCount": 40,
      "definitionsUpdated": 40,
      "owadPhrasesUpdated": 40,
      "distractorsUpdated": 40,
      "errors": 0,
      "startTime": 1742097193808,
      "endTime": 1742097233754,
      "elapsedTimeMs": 39946,
      "elapsedTimeMin": 0.7
    },
    {
      "batchNumber": 45,
      "wordCount": 40,
      "definitionsUpdated": 40,
      "owadPhrasesUpdated": 40,
      "distractorsUpdated": 40,
      "errors": 0,
      "startTime": 1742097234062,
      "endTime": 1742097277490,
      "elapsedTimeMs": 43428,
      "elapsedTimeMin": 0.7
    }
  ],
  "currentBatch": 45,
  "endTime": 1742097277490,
  "totalTimeMs": 1806091,
  "totalTimeMin": 30
}