[
  {
    "id": 26,
    "word": "craps",
    "pos": "noun"
  },
  {
    "id": 27,
    "word": "cannon",
    "pos": "noun"
  },
  {
    "id": 28,
    "word": "pool",
    "pos": "noun"
  },
  {
    "id": 29,
    "word": "checkers",
    "pos": "noun"
  },
  {
    "id": 30,
    "word": "chess",
    "pos": "noun"
  },
  {
    "id": 31,
    "word": "roulette",
    "pos": "noun"
  },
  {
    "id": 32,
    "word": "rag",
    "pos": "noun"
  },
  {
    "id": 33,
    "word": "festival",
    "pos": "noun"
  },
  {
    "id": 34,
    "word": "demonstration",
    "pos": "noun"
  },
  {
    "id": 35,
    "word": "fair",
    "pos": "noun"
  },
  {
    "id": 36,
    "word": "show",
    "pos": "noun"
  },
  {
    "id": 37,
    "word": "production",
    "pos": "noun"
  },
  {
    "id": 38,
    "word": "strip",
    "pos": "noun"
  },
  {
    "id": 39,
    "word": "charleston",
    "pos": "noun"
  },
  {
    "id": 40,
    "word": "waltz",
    "pos": "noun"
  },
  {
    "id": 41,
    "word": "jig",
    "pos": "noun"
  },
  {
    "id": 42,
    "word": "ire",
    "pos": "noun"
  },
  {
    "id": 43,
    "word": "reel",
    "pos": "noun"
  },
  {
    "id": 44,
    "word": "intonation",
    "pos": "noun"
  },
  {
    "id": 45,
    "word": "strain",
    "pos": "noun"
  },
  {
    "id": 46,
    "word": "program",
    "pos": "noun"
  },
  {
    "id": 47,
    "word": "song",
    "pos": "noun"
  },
  {
    "id": 48,
    "word": "bow",
    "pos": "noun"
  },
  {
    "id": 49,
    "word": "enactment",
    "pos": "noun"
  },
  {
    "id": 50,
    "word": "bill",
    "pos": "noun"
  },
  {
    "id": 51,
    "word": "tumult",
    "pos": "noun"
  },
  {
    "id": 52,
    "word": "programme",
    "pos": "noun"
  },
  {
    "id": 53,
    "word": "havoc",
    "pos": "noun"
  },
  {
    "id": 54,
    "word": "turmoil",
    "pos": "noun"
  },
  {
    "id": 55,
    "word": "ado",
    "pos": "noun"
  },
  {
    "id": 56,
    "word": "figure",
    "pos": "noun"
  },
  {
    "id": 57,
    "word": "blocking",
    "pos": "noun"
  },
  {
    "id": 58,
    "word": "interference",
    "pos": "noun"
  },
  {
    "id": 59,
    "word": "bustle",
    "pos": "noun"
  },
  {
    "id": 60,
    "word": "fit",
    "pos": "noun"
  },
  {
    "id": 61,
    "word": "block",
    "pos": "noun"
  },
  {
    "id": 62,
    "word": "putting",
    "pos": "noun"
  },
  {
    "id": 63,
    "word": "breeze",
    "pos": "noun"
  },
  {
    "id": 64,
    "word": "work",
    "pos": "noun"
  },
  {
    "id": 65,
    "word": "utility",
    "pos": "noun"
  },
  {
    "id": 66,
    "word": "paperwork",
    "pos": "noun"
  },
  {
    "id": 67,
    "word": "office",
    "pos": "noun"
  },
  {
    "id": 68,
    "word": "place",
    "pos": "noun"
  },
  {
    "id": 69,
    "word": "line",
    "pos": "noun"
  },
  {
    "id": 70,
    "word": "situation",
    "pos": "noun"
  },
  {
    "id": 71,
    "word": "admiralty",
    "pos": "noun"
  },
  {
    "id": 72,
    "word": "residency",
    "pos": "noun"
  },
  {
    "id": 73,
    "word": "trade",
    "pos": "noun"
  },
  {
    "id": 74,
    "word": "craft",
    "pos": "noun"
  },
  {
    "id": 75,
    "word": "furnishing",
    "pos": "noun"
  },
  {
    "id": 76,
    "word": "plum",
    "pos": "noun"
  },
  {
    "id": 77,
    "word": "prefecture",
    "pos": "noun"
  },
  {
    "id": 78,
    "word": "regency",
    "pos": "noun"
  },
  {
    "id": 79,
    "word": "education",
    "pos": "noun"
  },
  {
    "id": 80,
    "word": "labour",
    "pos": "noun"
  },
  {
    "id": 81,
    "word": "trouble",
    "pos": "noun"
  },
  {
    "id": 82,
    "word": "medium",
    "pos": "noun"
  },
  {
    "id": 83,
    "word": "theology",
    "pos": "noun"
  },
  {
    "id": 84,
    "word": "labor",
    "pos": "noun"
  },
  {
    "id": 85,
    "word": "struggle",
    "pos": "noun"
  },
  {
    "id": 86,
    "word": "substituting",
    "pos": "noun"
  },
  {
    "id": 87,
    "word": "set",
    "pos": "noun"
  },
  {
    "id": 88,
    "word": "clean",
    "pos": "noun"
  },
  {
    "id": 89,
    "word": "yoga",
    "pos": "noun"
  },
  {
    "id": 90,
    "word": "empiricism",
    "pos": "noun"
  },
  {
    "id": 91,
    "word": "count",
    "pos": "noun"
  },
  {
    "id": 92,
    "word": "microscopy",
    "pos": "noun"
  },
  {
    "id": 93,
    "word": "search",
    "pos": "noun"
  },
  {
    "id": 94,
    "word": "survey",
    "pos": "noun"
  },
  {
    "id": 95,
    "word": "tabulation",
    "pos": "noun"
  },
  {
    "id": 96,
    "word": "aid",
    "pos": "noun"
  },
  {
    "id": 97,
    "word": "study",
    "pos": "noun"
  },
  {
    "id": 98,
    "word": "titration",
    "pos": "noun"
  },
  {
    "id": 99,
    "word": "hemodialysis",
    "pos": "noun"
  },
  {
    "id": 100,
    "word": "intervention",
    "pos": "noun"
  },
  {
    "id": 101,
    "word": "facial",
    "pos": "noun"
  },
  {
    "id": 102,
    "word": "implantation",
    "pos": "noun"
  },
  {
    "id": 103,
    "word": "treatment",
    "pos": "noun"
  },
  {
    "id": 104,
    "word": "hospitalization",
    "pos": "noun"
  },
  {
    "id": 105,
    "word": "surgery",
    "pos": "noun"
  },
  {
    "id": 106,
    "word": "incision",
    "pos": "noun"
  },
  {
    "id": 107,
    "word": "section",
    "pos": "noun"
  },
  {
    "id": 108,
    "word": "justice",
    "pos": "noun"
  },
  {
    "id": 109,
    "word": "irrigation",
    "pos": "noun"
  },
  {
    "id": 110,
    "word": "neurosurgery",
    "pos": "noun"
  },
  {
    "id": 111,
    "word": "osteotomy",
    "pos": "noun"
  },
  {
    "id": 112,
    "word": "administration",
    "pos": "noun"
  },
  {
    "id": 113,
    "word": "dressing",
    "pos": "noun"
  },
  {
    "id": 114,
    "word": "hospice",
    "pos": "noun"
  },
  {
    "id": 115,
    "word": "flooding",
    "pos": "noun"
  },
  {
    "id": 116,
    "word": "colonic",
    "pos": "noun"
  },
  {
    "id": 117,
    "word": "psychotherapy",
    "pos": "noun"
  },
  {
    "id": 118,
    "word": "radiotherapy",
    "pos": "noun"
  },
  {
    "id": 119,
    "word": "irradiation",
    "pos": "noun"
  },
  {
    "id": 120,
    "word": "refrigeration",
    "pos": "noun"
  },
  {
    "id": 121,
    "word": "rubbing",
    "pos": "noun"
  },
  {
    "id": 122,
    "word": "covering",
    "pos": "noun"
  },
  {
    "id": 123,
    "word": "loading",
    "pos": "noun"
  },
  {
    "id": 124,
    "word": "radiation",
    "pos": "noun"
  },
  {
    "id": 125,
    "word": "ect",
    "pos": "noun"
  }
]